ajax_requester/__init__.py
ajax_requester/cURL_request.py
ajax_requester/requester.py
ajax_requester-0.5.dist-info/METADATA
ajax_requester-0.5.dist-info/WHEEL
ajax_requester-0.5.dist-info/top_level.txt
ajax_requester-0.5.dist-info/RECORD
