Metadata-Version: 2.1
Name: ajax_requester
Version: 0.5
Summary: A simple library to handle AJAX requests with cookies
Home-page: https://github.com/yourusername/ajax_requester
Author: Fyah
Author-email: 727475183@qq.com
Classifier: Programming Language :: Python :: 3
Classifier: License :: OSI Approved :: MIT License
Classifier: Operating System :: OS Independent
Requires-Python: >=3.6
Requires-Dist: requests
